mcp_wizard/__init__.py
mcp_wizard/cli.py
mcp_wizard/config.py
mcp_wizard/config.py.old
mcp_wizard/templates.py
mcp_wizard/ui.py
mcp_wizard/wizard.py
mcp_config_wizard-0.2.1.dist-info/METADATA
mcp_config_wizard-0.2.1.dist-info/WHEEL
mcp_config_wizard-0.2.1.dist-info/entry_points.txt
mcp_config_wizard-0.2.1.dist-info/RECORD
