Metadata-Version: 2.4
Name: mcp-config-wizard
Version: 0.2.1
Summary: Easily configure MCP servers through a beautiful interactive CLI
Project-URL: Homepage, https://github.com/your-username/mcp-config-wizard
Project-URL: Repository, https://github.com/your-username/mcp-config-wizard
Author: MCP Wizard Team
License: MIT
Keywords: ai,claude,cli,mcp,model-context-protocol,wizard
Classifier: Development Status :: 4 - Beta
Classifier: Environment :: Console
Classifier: Intended Audience :: Developers
Classifier: License :: OSI Approved :: MIT License
Classifier: Operating System :: OS Independent
Classifier: Programming Language :: Python :: 3
Classifier: Programming Language :: Python :: 3.8
Classifier: Programming Language :: Python :: 3.9
Classifier: Programming Language :: Python :: 3.10
Classifier: Programming Language :: Python :: 3.11
Classifier: Programming Language :: Python :: 3.12
Classifier: Programming Language :: Python :: 3.13
Classifier: Programming Language :: Python :: 3.14
Classifier: Topic :: Software Development :: Libraries :: Python Modules
Classifier: Topic :: Utilities
Requires-Python: >=3.8
Requires-Dist: platformdirs>=4.0.0
Requires-Dist: questionary>=2.0.0
Requires-Dist: rich>=13.0.0
